doinspect/__init__.py
doinspect/cli.py
doinspect/inspector.py
doinspect-0.1.5.dist-info/LICENSE
doinspect-0.1.5.dist-info/METADATA
doinspect-0.1.5.dist-info/WHEEL
doinspect-0.1.5.dist-info/entry_points.txt
doinspect-0.1.5.dist-info/top_level.txt
doinspect-0.1.5.dist-info/RECORD
