Metadata-Version: 2.2
Name: doinspect
Version: 0.1.5
Summary: A CLI tool to inspect running Docker containers
Home-page: https://github.com/srmaarnav/doinspect
Author: Arnav Sharma
Author-email: mail@arnavsharma.com.np
Classifier: Programming Language :: Python :: 3
Classifier: License :: OSI Approved :: MIT License
Classifier: Operating System :: OS Independent
Requires-Python: >=3.6
License-File: LICENSE
Requires-Dist: docker
Dynamic: author
Dynamic: author-email
Dynamic: classifier
Dynamic: description
Dynamic: description-content-type
Dynamic: home-page
Dynamic: requires-dist
Dynamic: requires-python
Dynamic: summary
